sus_adk/__init__.py
sus_adk/__main__.py
sus_adk/agent.py
sus_adk/browser_cookie.py
sus_adk/chain.py
sus_adk/memory.py
sus_adk/provider.py
sus_adk/session.py
sus_adk/tool.py
sus_adk/vector_memory.py
sus_adk/providers/__init__.py
sus_adk/providers/generic.py
sus_adk-0.2.2.dist-info/METADATA
sus_adk-0.2.2.dist-info/WHEEL
sus_adk-0.2.2.dist-info/top_level.txt
sus_adk-0.2.2.dist-info/RECORD
