Metadata-Version: 2.4
Name: sus-adk
Version: 0.2.2
Summary: A modular sus-adk for LLM interaction via cookies, inspired by LangChain and Google-ADK.
Home-page: https://github.com/yourusername/agentic-framework
Author: Your Name
Author-email: Venkat Bulusu <venkatbulusu96@gmail.com>
License: MIT
Requires-Python: >=3.7
Requires-Dist: requests
Dynamic: author
Dynamic: home-page
Dynamic: requires-python
